misc_utils/__init__.py
misc_utils/datetime_utils.py
misc_utils/decorator_utils.py
misc_utils/iterable_utils.py
misc_utils/json_dict.py
misc_utils/media_utils.py
misc_utils/misc_utils.py
misc_utils/networking_utils.py
misc_utils/param_utils.py
misc_utils/string_utils.py
miscellaneous_utils-0.3.10.dist-info/LICENSE
miscellaneous_utils-0.3.10.dist-info/METADATA
miscellaneous_utils-0.3.10.dist-info/WHEEL
miscellaneous_utils-0.3.10.dist-info/RECORD
