Metadata-Version: 2.1
Name: miscellaneous-utils
Version: 0.3.10
Summary: Random collection of utilities that I've found useful.
Home-page: https://github.com/nicholas-mischke/miscellaneous-utils
Author: Nicholas Mischke
Author-email: nmischkework@proton.me
Requires-Python: >=3.9
Classifier: Programming Language :: Python :: 3
Classifier: Programming Language :: Python :: 3.9
Classifier: Programming Language :: Python :: 3.10
Classifier: Programming Language :: Python :: 3.11
Classifier: Programming Language :: Python :: 3.12
Requires-Dist: dateparser (>=1.2.0,<2.0.0)
Requires-Dist: numpy (>=1.26.1,<2.0.0)
Requires-Dist: pendulum (>=3.0.0,<4.0.0)
Requires-Dist: typer (>=0.9.0,<0.10.0)
Project-URL: Repository, https://github.com/nicholas-mischke/miscellaneous-utils
